{
  "project_info": {
    "project_number": "744779973816",
    "project_id": "verbose-customer",
    "storage_bucket": "verbose-customer.appspot.com"
  },
  "client": [
    {
      "client_info": {
        "mobilesdk_app_id": "1:744779973816:android:5c7f0c4756f7c1f3ad604d",
        "android_client_info": {
          "package_name": "com.example.verbose_user"
        }
      },
      "oauth_client": [
        {
          "client_id": "744779973816-eb9a8plvl2m2cskd8eqbl4bmj8d6v5re.apps.googleusercontent.com",
          "client_type": 3
        }
      ],
      "api_key": [
        {
          "current_key": "AIzaSyApDpqQMD2zM3cWiYiaieIoYR8uXwagAH4"
        }
      ],
      "services": {
        "appinvite_service": {
          "other_platform_oauth_client": [
            {
              "client_id": "744779973816-eb9a8plvl2m2cskd8eqbl4bmj8d6v5re.apps.googleusercontent.com",
              "client_type": 3
            }
          ]
        }
      }
    }
  ],
  "configuration_version": "1"
}